videobox/__init__.py
videobox/api.py
videobox/bt.py
videobox/filters.py
videobox/iso639.py
videobox/models.py
videobox/scraper.py
videobox/sync.py
videobox/trackers.txt
videobox/main/__init__.py
videobox/main/announcer.py
videobox/main/queries.py
videobox/main/routes.py
videobox/static/app-icon.png
videobox/static/app.css
videobox/static/app.css.map
videobox/static/app.js
videobox/static/app.js.map
videobox/static/app.webmanifest
videobox/static/apple-touch-icon.png
videobox/static/default-poster.png
videobox/static/default-still.png
videobox/static/favicon.png
videobox/static/favicon.svg
videobox/static/icon-check-bold.svg
videobox/static/icon-check.svg
videobox/static/icon-close-bold.svg
videobox/static/icon-close.svg
videobox/static/icon-download-bold.svg
videobox/static/icon-download.svg
videobox/static/icon-file-bold.svg
videobox/static/icon-file-video-bold.svg
videobox/static/icon-file-video.svg
videobox/static/icon-file.svg
videobox/static/icon-gear-bold.svg
videobox/static/icon-gear.svg
videobox/static/icon-grid-bold.svg
videobox/static/icon-grid.svg
videobox/static/icon-heart-bold.svg
videobox/static/icon-heart-break-bold.svg
videobox/static/icon-heart-break.svg
videobox/static/icon-heart.svg
videobox/static/icon-heartbeat-bold.svg
videobox/static/icon-heartbeat.svg
videobox/static/icon-hourglass-bold.svg
videobox/static/icon-hourglass.svg
videobox/static/icon-info-bold.svg
videobox/static/icon-info.svg
videobox/static/icon-list-bold.svg
videobox/static/icon-list.svg
videobox/static/icon-magnet-bold.svg
videobox/static/icon-magnet.svg
videobox/static/icon-search-bold.svg
videobox/static/icon-search.svg
videobox/static/icon-sort-asc.svg
videobox/static/icon-sort-desc.svg
videobox/static/icon-tag-bold.svg
videobox/static/icon-tag.svg
videobox/static/icon-trash-bold.svg
videobox/static/icon-trash.svg
videobox/static/icon-trend-down-bold.svg
videobox/static/icon-trend-down.svg
videobox/static/icon-trend-up-bold.svg
videobox/static/icon-trend-up.svg
videobox-0.8.2.dist-info/licenses/LICENSE
videobox-0.8.2.dist-info/METADATA
videobox-0.8.2.dist-info/WHEEL
videobox-0.8.2.dist-info/entry_points.txt
videobox-0.8.2.dist-info/top_level.txt
videobox-0.8.2.dist-info/RECORD
