Metadata-Version: 2.4
Name: videobox
Version: 0.8.2
Summary: Easy TV series download
Author: Andrea Peltrin
Project-URL: Homepage, https://github.com/passiomatic/videobox
Project-URL: Bug Tracker, https://github.com/passiomatic/videobox/issues
Classifier: Programming Language :: Python :: 3
Classifier: License :: OSI Approved :: BSD License
Classifier: Operating System :: OS Independent
Classifier: Development Status :: 4 - Beta
Classifier: Environment :: Console
Classifier: Environment :: Web Environment
Classifier: Framework :: Flask
Requires-Python: >=3.9
License-File: LICENSE
Requires-Dist: peewee<4,>=3.15.4
Requires-Dist: urllib3<2
Requires-Dist: requests<3,>=2.31.0
Requires-Dist: flask<3,>=2.3.3
Requires-Dist: waitress<4,>=3.0.1
Requires-Dist: tomli<3,>=2.0.1
Requires-Dist: tomli-w<2,>=1.0.0
Requires-Dist: chardet==5.2.0
Requires-Dist: libtorrent<2.1,>=2.0.9
Dynamic: license-file
